my_utilities/__init__.py
my_utilities/cache/__init__.py
my_utilities/iterables/__init__.py
my_utilities/iterables/chunk.py
my_utilities/iterables/split.py
my_utilities/jwt_handler/__init__.py
my_utilities/jwt_handler/auth_cache_handler.py
my_utilities/jwt_handler/exc.py
my_utilities/jwt_handler/jwt_handler.py
my_utilities/mixins/__init__.py
my_utilities/mixins/compact_pydantic_serializer.py
my_utilities/mixins/tst_mode.py
my_utilities/probability/__init__.py
my_utilities/probability/probability_event_occurring.py
my_utilities/singleton/__init__.py
my_utilities/types/__init__.py
my_utilities/types/ttl_dict.py
my_utilities/view/__init__.py
my_utilities/view/converter_size_to_pretty_view.py
my_utilities-0.1.4.dist-info/licenses/LICENSE
my_utilities-0.1.4.dist-info/METADATA
my_utilities-0.1.4.dist-info/WHEEL
my_utilities-0.1.4.dist-info/top_level.txt
my_utilities-0.1.4.dist-info/RECORD
