Metadata-Version: 2.4
Name: my_utilities
Version: 0.1.4
Summary: Add your description here
Requires-Python: >=3.12
License-File: LICENSE
Requires-Dist: pydantic>=2.12.3
Requires-Dist: pyjwt>=2.10.1
Dynamic: license-file
